simple_interest/__init__.py
simple_interest/simple_interest.py
simple_interest-0.1.1.dist-info/METADATA
simple_interest-0.1.1.dist-info/WHEEL
simple_interest-0.1.1.dist-info/top_level.txt
simple_interest-0.1.1.dist-info/RECORD
